Workbook

Sheet Summary
A1: Summary
A2: 2027 ICT plan · Business objectives and planned spend
A4: Overview | B4: Detail
A5: Organisation | B5: Synthetic demo organisation
A6: Role | B6: CIO
A7: Planning period | B7: 2027-01 to 2027-12
A8: Reporting currency | B8: USD
A9: Generated at (UTC) | B9: 2026-10-14T03:34:43.546Z
A10: Planned spend so far | B10: =SUM('Budget by objective'!K8,'Budget by objective'!K9,'Budget by objective'!K11) -> 14000
A11: Lines unpriced | B11: =COUNTIF('Monthly cash profile'!O5,"Unpriced")+COUNTIF('Monthly cash profile'!O6,"Unpriced")+COUNTIF('Monthly cash profile'!O7,"Unpriced") -> 2
A12: Lines awaiting exchange rates | B12: 0
A13: Business objectives
A14: Open four branches on time | B14: All four branches trading by Q3 2027
A15: Cut outages | B15: Branch downtime under 4 hours a month
A16: How to read this
A17: Totals | B17: Accepted lines only. Unpriced and unconverted items are excluded from reporting totals; the total is incomplete until they are resolved.
A18: Adjusting the budget | B18: Edit quantity and unit price on Budget by objective. Monthly cash, objective subtotals and planned spend recalculate. Timing and frequency changes require a fresh export.
A19: Assumptions | B19: Cash basis; each payment rounded to two decimals. Source prices retain their precision, displayed to two decimals. Bundle prices apply once per payment, irrespective of quantity. Tax is unresolved; no additional tax or exchange rates have been assumed.
A20: Privacy | B20: This workbook contains your accepted plan and open questions. Keep it private unless you choose to share it.
A21: Prepared with | B21: Prepared with Budget Buddy, an AI advisor run by Kenac Computer Systems. Prices are sourced as shown; unpriced items are excluded from totals.

Sheet Budget by objective
A1: Budget by objective
A2: Accepted lines · Period totals in the line's currency · Reporting currency: USD
A4: Item | B4: Category | C4: Qty | D4: Unit | E4: Frequency | F4: Timing | G4: Unit price | H4: Currency | I4: Evidence | J4: Supplier | K4: Period total | L4: Price basis
A5: Open four branches on time
A6: Cut outages
A7: Solar and UPS at every branch · Fund
A8: Solar + UPS kit, per branch | B8: Hardware | C8: 4 | D8: branches | E8: One off | F8: 2027-03 | G8: 3500 | H8: USD | I8: Own estimate | J8: Not specified | K8: ='Monthly cash profile'!O5 -> 14000 | L8: Per unit
A9: Installation and commissioning | B9: Professional services | C9: 4 | D9: branches | E9: One off | F9: 2027-03 | G9: Unpriced | H9: USD | I9: Unpriced | J9: Not specified | K9: ='Monthly cash profile'!O6 -> Unpriced | L9: Per unit
A10: Keep the firewall subscription current · Fund
A11: Firewall subscription renewal | B11: Cybersecurity | C11: 1 | D11: Not specified | E11: Annual | F11: 2027-08 | G11: Unpriced | H11: USD | I11: Unpriced | J11: Not specified | K11: ='Monthly cash profile'!O7 -> Unpriced | L11: Bundle
A12: Objective subtotal so far | H12: USD | K12: =SUM(K8,K9,K11) -> 14000
A14: Prepared with Budget Buddy, an AI advisor run by Kenac Computer Systems. Prices are sourced as shown; unpriced items are excluded from totals.

Sheet Monthly cash profile
A1: Monthly cash profile
A2: Engine cash schedule · Amounts in each line's original currency · Totals kept separate by currency
A4: Item | B4: Currency | C4: 2027-01 | D4: 2027-02 | E4: 2027-03 | F4: 2027-04 | G4: 2027-05 | H4: 2027-06 | I4: 2027-07 | J4: 2027-08 | K4: 2027-09 | L4: 2027-10 | M4: 2027-11 | N4: 2027-12 | O4: Period total
A5: Solar + UPS kit, per branch | B5: USD | C5: =IF(AND(ISNUMBER('Budget by objective'!G8),ISNUMBER('Budget by objective'!C8)),0,"Unpriced") -> 0 | D5: =IF(AND(ISNUMBER('Budget by objective'!G8),ISNUMBER('Budget by objective'!C8)),0,"Unpriced") -> 0 | E5: =IF(AND(ISNUMBER('Budget by objective'!G8),ISNUMBER('Budget by objective'!C8)),ROUND('Budget by objective'!G8*'Budget by objective'!C8,2),"Unpriced") -> 14000 | F5: =IF(AND(ISNUMBER('Budget by objective'!G8),ISNUMBER('Budget by objective'!C8)),0,"Unpriced") -> 0 | G5: =IF(AND(ISNUMBER('Budget by objective'!G8),ISNUMBER('Budget by objective'!C8)),0,"Unpriced") -> 0 | H5: =IF(AND(ISNUMBER('Budget by objective'!G8),ISNUMBER('Budget by objective'!C8)),0,"Unpriced") -> 0 | I5: =IF(AND(ISNUMBER('Budget by objective'!G8),ISNUMBER('Budget by objective'!C8)),0,"Unpriced") -> 0 | J5: =IF(AND(ISNUMBER('Budget by objective'!G8),ISNUMBER('Budget by objective'!C8)),0,"Unpriced") -> 0 | K5: =IF(AND(ISNUMBER('Budget by objective'!G8),ISNUMBER('Budget by objective'!C8)),0,"Unpriced") -> 0 | L5: =IF(AND(ISNUMBER('Budget by objective'!G8),ISNUMBER('Budget by objective'!C8)),0,"Unpriced") -> 0 | M5: =IF(AND(ISNUMBER('Budget by objective'!G8),ISNUMBER('Budget by objective'!C8)),0,"Unpriced") -> 0 | N5: =IF(AND(ISNUMBER('Budget by objective'!G8),ISNUMBER('Budget by objective'!C8)),0,"Unpriced") -> 0 | O5: =IF(COUNT(C5:N5)=COLUMNS(C5:N5),SUM(C5:N5),"Unpriced") -> 14000
A6: Installation and commissioning | B6: USD | C6: =IF(AND(ISNUMBER('Budget by objective'!G9),ISNUMBER('Budget by objective'!C9)),0,"Unpriced") -> Unpriced | D6: =IF(AND(ISNUMBER('Budget by objective'!G9),ISNUMBER('Budget by objective'!C9)),0,"Unpriced") -> Unpriced | E6: =IF(AND(ISNUMBER('Budget by objective'!G9),ISNUMBER('Budget by objective'!C9)),ROUND('Budget by objective'!G9*'Budget by objective'!C9,2),"Unpriced") -> Unpriced | F6: =IF(AND(ISNUMBER('Budget by objective'!G9),ISNUMBER('Budget by objective'!C9)),0,"Unpriced") -> Unpriced | G6: =IF(AND(ISNUMBER('Budget by objective'!G9),ISNUMBER('Budget by objective'!C9)),0,"Unpriced") -> Unpriced | H6: =IF(AND(ISNUMBER('Budget by objective'!G9),ISNUMBER('Budget by objective'!C9)),0,"Unpriced") -> Unpriced | I6: =IF(AND(ISNUMBER('Budget by objective'!G9),ISNUMBER('Budget by objective'!C9)),0,"Unpriced") -> Unpriced | J6: =IF(AND(ISNUMBER('Budget by objective'!G9),ISNUMBER('Budget by objective'!C9)),0,"Unpriced") -> Unpriced | K6: =IF(AND(ISNUMBER('Budget by objective'!G9),ISNUMBER('Budget by objective'!C9)),0,"Unpriced") -> Unpriced | L6: =IF(AND(ISNUMBER('Budget by objective'!G9),ISNUMBER('Budget by objective'!C9)),0,"Unpriced") -> Unpriced | M6: =IF(AND(ISNUMBER('Budget by objective'!G9),ISNUMBER('Budget by objective'!C9)),0,"Unpriced") -> Unpriced | N6: =IF(AND(ISNUMBER('Budget by objective'!G9),ISNUMBER('Budget by objective'!C9)),0,"Unpriced") -> Unpriced | O6: =IF(COUNT(C6:N6)=COLUMNS(C6:N6),SUM(C6:N6),"Unpriced") -> Unpriced
A7: Firewall subscription renewal | B7: USD | C7: =IF(AND(ISNUMBER('Budget by objective'!G11),ISNUMBER(1)),0,"Unpriced") -> Unpriced | D7: =IF(AND(ISNUMBER('Budget by objective'!G11),ISNUMBER(1)),0,"Unpriced") -> Unpriced | E7: =IF(AND(ISNUMBER('Budget by objective'!G11),ISNUMBER(1)),0,"Unpriced") -> Unpriced | F7: =IF(AND(ISNUMBER('Budget by objective'!G11),ISNUMBER(1)),0,"Unpriced") -> Unpriced | G7: =IF(AND(ISNUMBER('Budget by objective'!G11),ISNUMBER(1)),0,"Unpriced") -> Unpriced | H7: =IF(AND(ISNUMBER('Budget by objective'!G11),ISNUMBER(1)),0,"Unpriced") -> Unpriced | I7: =IF(AND(ISNUMBER('Budget by objective'!G11),ISNUMBER(1)),0,"Unpriced") -> Unpriced | J7: =IF(AND(ISNUMBER('Budget by objective'!G11),ISNUMBER(1)),ROUND('Budget by objective'!G11*1,2),"Unpriced") -> Unpriced | K7: =IF(AND(ISNUMBER('Budget by objective'!G11),ISNUMBER(1)),0,"Unpriced") -> Unpriced | L7: =IF(AND(ISNUMBER('Budget by objective'!G11),ISNUMBER(1)),0,"Unpriced") -> Unpriced | M7: =IF(AND(ISNUMBER('Budget by objective'!G11),ISNUMBER(1)),0,"Unpriced") -> Unpriced | N7: =IF(AND(ISNUMBER('Budget by objective'!G11),ISNUMBER(1)),0,"Unpriced") -> Unpriced | O7: =IF(COUNT(C7:N7)=COLUMNS(C7:N7),SUM(C7:N7),"Unpriced") -> Unpriced
A8: Total so far | B8: USD | C8: =SUM(C5,C6,C7) -> 0 | D8: =SUM(D5,D6,D7) -> 0 | E8: =SUM(E5,E6,E7) -> 14000 | F8: =SUM(F5,F6,F7) -> 0 | G8: =SUM(G5,G6,G7) -> 0 | H8: =SUM(H5,H6,H7) -> 0 | I8: =SUM(I5,I6,I7) -> 0 | J8: =SUM(J5,J6,J7) -> 0 | ... O8: =SUM(O5,O6,O7) -> 14000
A10: Prepared with Budget Buddy, an AI advisor run by Kenac Computer Systems. Prices are sourced as shown; unpriced items are excluded from totals.

Sheet Evidence register
A1: Evidence register
A2: Prices as captured · Check validity with the supplier before committing funds
A4: Item | B4: Evidence | C4: Reference | D4: Captured at | E4: Valid until | F4: Validity at export | G4: Supplier | H4: Unit price | I4: Currency
A5: Solar + UPS kit, per branch | B5: Own estimate | C5: Own estimate | D5: 2026-10-14T03:34:43.236Z | E5: Not supplied | F5: Confirm with supplier | G5: Not specified | H5: 3500 | I5: USD
A7: Prepared with Budget Buddy, an AI advisor run by Kenac Computer Systems. Prices are sourced as shown; unpriced items are excluded from totals.

Sheet Open questions
A1: Open questions
A2: Resolve these before approving the budget · Proposed items carry no commitment
A4: Type | B4: Item | C4: Question or caution
A5: Unpriced | B5: Installation and commissioning | C5: Request a quote, attach a sourced price or enter your own labelled estimate.
A6: Unpriced | B6: Firewall subscription renewal | C6: Request a quote, attach a sourced price or enter your own labelled estimate.
A8: Prepared with Budget Buddy, an AI advisor run by Kenac Computer Systems. Prices are sourced as shown; unpriced items are excluded from totals.
